momapy/__about__.py
momapy/__init__.py
momapy/animating.py
momapy/builder.py
momapy/coloring.py
momapy/core.py
momapy/drawing.py
momapy/geometry.py
momapy/monitoring.py
momapy/positioning.py
momapy/styling.py
momapy/testing.py
momapy/utils.py
momapy/celldesigner/__init__.py
momapy/celldesigner/core.py
momapy/celldesigner/io/__init__.py
momapy/celldesigner/io/celldesigner.py
momapy/celldesigner/io/pickle.py
momapy/io/__init__.py
momapy/io/core.py
momapy/meta/__init__.py
momapy/meta/arcs.py
momapy/meta/nodes.py
momapy/meta/shapes.py
momapy/rendering/__init__.py
momapy/rendering/_cairo.py
momapy/rendering/cairo.py
momapy/rendering/core.py
momapy/rendering/skia.py
momapy/rendering/svg_native.py
momapy/sbgn/__init__.py
momapy/sbgn/af.py
momapy/sbgn/core.py
momapy/sbgn/pd.py
momapy/sbgn/utils.py
momapy/sbgn/io/__init__.py
momapy/sbgn/io/pickle.py
momapy/sbgn/io/sbgnml.py
momapy/sbgn/styling/.sbgned.css.swo
momapy/sbgn/styling/__init__.py
momapy/sbgn/styling/cs_black_and_white.css
momapy/sbgn/styling/cs_default.css
momapy/sbgn/styling/default.css
momapy/sbgn/styling/default_colorscheme.css
momapy/sbgn/styling/fs_shadows.css
momapy/sbgn/styling/newt.css
momapy/sbgn/styling/newt_no_cs.css
momapy/sbgn/styling/sbgned.css
momapy/sbgn/styling/sbgned_no_cs.css
momapy/sbgn/styling/shadows.css
momapy/sbgn/styling/white_colorscheme.css
momapy/sbml/__init__.py
momapy/sbml/core.py
momapy/sbml/io/__init__.py
momapy/sbml/io/sbml.py
momapy-0.2.5.dist-info/METADATA
momapy-0.2.5.dist-info/WHEEL
momapy-0.2.5.dist-info/licenses/COPYING
momapy-0.2.5.dist-info/RECORD
