Metadata-Version: 2.4
Name: momapy
Version: 0.2.5
Summary: A library to work with molecular maps
Project-URL: Homepage, https://github.com/adrienrougny/momapy
Project-URL: Issues, https://github.com/adrienrougny/momapy/issues
Author-email: Adrien Rougny <adrienrougny@gmail.com>
License: GPL-3.0-or-later
License-File: COPYING
Classifier: License :: OSI Approved :: GNU General Public License v3 or later (GPLv3+)
Classifier: Operating System :: OS Independent
Classifier: Programming Language :: Python :: 3
Classifier: Programming Language :: Python :: 3.10
Classifier: Programming Language :: Python :: 3.11
Classifier: Programming Language :: Python :: 3.12
Requires-Python: >=3.10
Requires-Dist: bezier>=2023.7.28
Requires-Dist: colorama>=0.4.6
Requires-Dist: frozendict>=2.3.10
Requires-Dist: lxml>=5.3.2
Requires-Dist: matplotlib>=3.10.8
Requires-Dist: numpy>=1.26.2
Requires-Dist: pyparsing>=3.1.1
Requires-Dist: shapely>=2.0.2
Requires-Dist: typing-extensions>=4.15.0
Requires-Dist: uharfbuzz>=0.53.0
Provides-Extra: all
Requires-Dist: pycairo>=1.29.0; extra == 'all'
Requires-Dist: pygobject>=3.54.5; extra == 'all'
Requires-Dist: skia-python>=138.0; extra == 'all'
Provides-Extra: cairo
Requires-Dist: pycairo>=1.29.0; extra == 'cairo'
Requires-Dist: pygobject>=3.54.5; extra == 'cairo'
Provides-Extra: skia
Requires-Dist: skia-python>=138.0; extra == 'skia'
